{"type": "Feature", "id": 12523232, "geometry": {"type": "Point", "coordinates": [36.299999, 41.283329]}, "properties": {"woe:id": 12523232, "woe:parent_id": 2344351, "woe:name": "Samsun Airport", "woe:placetype": 14, "woe:placetype_name": "Airport", "woe:lang": "ENG", "iso:country": "TR", "meta:provider": ["geoplanet:7.3.1", "geoplanet:7.3.2", "geoplanet:7.4.0", "geoplanet:7.4.1", "geoplanet:7.5.1", "geoplanet:7.5.2", "geoplanet:7.6.0", "geoplanet:7.8.1", "geoplanet:7.9.0", "geoplanet:7.10.0", "geoplanet:8.0.0", "woeplanet:8.0.0"], "meta:indexed": "2020-08-20T20:26:30.453400", "woe:alias_ENG_V": ["SSX Airport", "SSX"], "meta:updated": "2020-10-14T11:45:57.646112", "woe:hierarchy": {"continent": 24865671, "country": 23424969, "town": 0, "planet": 1, "county": 29390625, "suburb": 0, "state": 2347307, "region": 0, "localadmin": 0}, "woe:timezone_id": 28350899, "woe:hash": "sz3ff52ug631", "woe:centroid": [36.299999, 41.283329], "geom:latitude": 41.283329, "geom:longitude": 36.299999, "geom:hash": "sz3ff52ug631", "woe:latitude": 41.283329, "geom:centroid": [36.299999, 41.283329], "woe:longitude": 36.299999, "woe:repo": "woeplanet-airport-tr", "geom:area": 0.0, "woe:scale": 19}}