{"type": "Feature", "id": 12517911, "properties": {"woe:id": 12517911, "woe:parent_id": 2343678, "woe:name": "Sakirpasa Airport", "woe:placetype": 14, "woe:placetype_name": "Airport", "woe:lang": "ENG", "iso:country": "TR", "meta:provider": ["geoplanet:7.4.0", "geoplanet:7.4.1", "geoplanet:7.5.1", "geoplanet:7.5.2", "geoplanet:7.6.0", "geoplanet:7.8.1", "geoplanet:7.9.0", "geoplanet:7.10.0", "geoplanet:8.0.0", "woeplanet:8.0.0"], "meta:indexed": "2020-08-21T00:44:23.383064", "woe:alias_ENG_V": ["Adana Sakirpasa Airport", "ADA", "ADA Airport"], "woe:alias_ITA_V": ["Aeroporto Adana Sakirpasa"], "woe:alias_UNK_V": ["Adana Sakirpasa Havalimani", "Adana Sakirpasa Repuloter", "Adana Sakirpasa Rep\u00fcl\u00f4t\u00e9r", "Port Lotniczy Adana Sakirpasa"], "woe:alias_DUT_V": ["Lughthaven Adana Sakirpasa"], "woe:alias_POR_V": ["Aeroporto de Adana Sakirpasa"], "meta:updated": "2020-08-22T02:49:32.365635", "woe:alias_GER_V": ["Adana Sakirpasa Flughafen"], "woe:alias_FRE_V": ["Aeroport Adana Sakirpasa"], "woe:alias_SPA_V": ["Aeropuerto Adana Sakirpasa"], "woe:hierarchy": {"continent": 24865671, "country": 23424969, "town": 0, "planet": 1, "county": 29390751, "suburb": 0, "state": 2347258, "region": 0, "localadmin": 0}, "woe:timezone_id": 28350899, "woe:hash": "sy947hxw0pfd", "woe:centroid": [35.298389, 36.983799], "geom:latitude": 36.983799, "geom:longitude": 35.298389, "geom:hash": "sy947hxw0pfd", "woe:latitude": 36.983799, "geom:centroid": [35.298389, 36.983799], "woe:longitude": 35.298389, "woe:repo": "woeplanet-airport-tr"}, "geometry": {"coordinates": [35.298389, 36.983799], "type": "Point"}}