{"type": "Feature", "id": 12517901, "geometry": {"type": "Point", "coordinates": [43.067501, 40.582802]}, "properties": {"woe:id": 12517901, "woe:parent_id": 2344165, "woe:name": "Kars (abandoned) Airport", "woe:placetype": 14, "woe:placetype_name": "Airport", "woe:lang": "ENG", "iso:country": "TR", "meta:provider": ["geoplanet:7.3.1", "geoplanet:7.3.2", "geoplanet:7.4.0", "geoplanet:7.4.1", "geoplanet:7.5.1", "geoplanet:7.5.2", "geoplanet:7.6.0", "geoplanet:7.8.1", "geoplanet:7.9.0", "geoplanet:7.10.0", "geoplanet:8.0.0", "woeplanet:8.0.0"], "meta:indexed": "2020-08-20T20:26:30.434185", "woe:alias_ENG_V": ["KSY Airport", "KSY", "Kars (abandoned)"], "meta:updated": "2020-10-14T11:45:57.661632", "woe:hierarchy": {"continent": 24865671, "country": 23424969, "town": 0, "planet": 1, "county": 29390971, "suburb": 0, "state": 2347291, "region": 0, "localadmin": 0}, "woe:timezone_id": 28350899, "woe:hash": "sznwu5bgcw87", "woe:centroid": [43.067501, 40.582802], "geom:latitude": 40.582802, "geom:longitude": 43.067501, "geom:hash": "sznwu5bgcw87", "woe:latitude": 40.582802, "geom:centroid": [43.067501, 40.582802], "woe:longitude": 43.067501, "woe:repo": "woeplanet-airport-tr", "geom:area": 0.0, "woe:scale": 19}}