{"type": "Feature", "id": 12517899, "properties": {"woe:id": 12517899, "woe:parent_id": 2344466, "woe:name": "Kaklic Airport", "woe:placetype": 14, "woe:placetype_name": "Airport", "woe:lang": "ENG", "iso:country": "TR", "meta:provider": ["geoplanet:7.3.1", "geoplanet:7.3.2", "geoplanet:7.4.0", "geoplanet:7.4.1", "geoplanet:7.5.1", "geoplanet:7.5.2", "geoplanet:7.6.0", "geoplanet:7.8.1", "geoplanet:7.9.0", "geoplanet:7.10.0", "geoplanet:8.0.0", "woeplanet:8.0.0"], "meta:indexed": "2020-08-20T20:26:30.432443", "woe:alias_ENG_V": ["IGL Airport", "IGL"], "meta:updated": "2020-08-22T02:49:32.351065", "woe:hierarchy": {"continent": 24865671, "country": 23424969, "town": 0, "planet": 1, "county": 29390233, "suburb": 0, "state": 2347290, "region": 0, "localadmin": 0}, "woe:timezone_id": 28350899, "woe:hash": "swg5juhsu7c8", "woe:centroid": [26.9778, 38.518902], "geom:latitude": 38.518902, "geom:longitude": 26.9778, "geom:hash": "swg5juhsu7c8", "woe:latitude": 38.518902, "geom:centroid": [26.9778, 38.518902], "woe:longitude": 26.9778, "woe:repo": "woeplanet-airport-tr"}, "geometry": {"coordinates": [26.9778, 38.518902], "type": "Point"}}