{"type": "Feature", "id": 12517889, "geometry": {"type": "Point", "coordinates": [32.988998, 40.109852]}, "properties": {"woe:id": 12517889, "woe:parent_id": 2343905, "woe:name": "Esenboga Airport", "woe:placetype": 14, "woe:placetype_name": "Airport", "woe:lang": "ENG", "iso:country": "TR", "meta:provider": ["geoplanet:7.3.1", "geoplanet:7.3.2", "geoplanet:7.4.0", "geoplanet:7.4.1", "geoplanet:7.5.1", "geoplanet:7.5.2", "geoplanet:7.6.0", "geoplanet:7.8.1", "geoplanet:7.9.0", "geoplanet:7.10.0", "geoplanet:8.0.0", "woeplanet:8.0.0"], "meta:indexed": "2020-08-20T20:26:30.466817", "woe:alias_ENG_V": ["ESB Airport", "ESB"], "woe:alias_ITA_V": ["Aeroporto Esenboga"], "woe:alias_UNK_V": ["Esenboga Havalimani", "Letiste Ankara-Esenboga", "Diethnes Aerodromio Esenmponga", "Esenboga Rep\u00fcl\u00f4t\u00e9r", "Esenboga Repuloter", "Port Lotniczy Ankara Esenboga", "Esenboga Aeroport", "Letisko Ankara-Esenboga"], "woe:alias_DUT_V": ["Luchthaven Ankara Esenboga"], "woe:alias_POR_V": ["Aeroporto de Esenboga"], "meta:updated": "2020-10-14T11:45:57.624396", "woe:alias_GER_V": ["Flughafen Ankara Esenboga"], "woe:alias_FRE_V": ["Aeroport Esenboga", "A\u00e9roport Esenboga"], "woe:alias_SPA_V": ["Aeropuerto Esenboga"], "woe:hierarchy": {"continent": 24865671, "country": 23424969, "town": 0, "planet": 1, "county": 29390243, "suburb": 0, "state": 2347263, "region": 0, "localadmin": 0}, "woe:timezone_id": 28350899, "woe:hash": "sxpkntvbg67f", "woe:centroid": [32.988998, 40.109852], "geom:latitude": 40.109852, "geom:longitude": 32.988998, "geom:hash": "sxpkntvbg67f", "woe:latitude": 40.109852, "geom:centroid": [32.988998, 40.109852], "woe:longitude": 32.988998, "woe:repo": "woeplanet-airport-tr", "geom:area": 0.0, "woe:scale": 19}}